Metadata-Version: 2.1
Name: Flask-SAML
Version: 0.5.0
Summary: Flask SAML integration
Home-page: https://bitbucket.org/asecurityteam/flask_saml
Author: Florian Ruechel
Author-email: fruechel@atlassian.com
Requires-Python: >=3.8
License-File: LICENSE.txt
